Workbook

Sheet Review
A1: GOLDEN EVALUATION BENCHMARK — ASSISTED HUMAN REVIEW WORKBOOK
A2: Total Messages: | B2: 200 | C2: Pending Review: | D2: =COUNTBLANK(D6:D205) | E2: Completed Review: | F2: =COUNTA(D6:D205) | G2: Completion %: | H2: =COUNTA(D6:D205)/200
A3: INSTRUCTIONS: Candidate columns (Soft Blue) provide machine proposals to accelerate review. Fill green columns (D, F, H, J, L, N) for human gold labels. Do NOT modify original text or IDs.
A5: message_id | B5: original_text | C5: assistant_proposed_intent | D5: my_final_intent | E5: assistant_proposed_language | F5: my_final_language | G5: assistant_proposed_conversation_state | H5: my_final_conversation_state | I5: assistant_proposed_escalate | J5: my_final_escalate | K5: assistant_proposed_is_security_alert | L5: my_final_is_security_alert | M5: assistant_proposed_priority | N5: my_final_priority | O5: assistant_proposed_reason | P5: assistant_confidence | Q5: assistant_ambiguity_note | R5: notes
A6: 1721 | B6: @AmazonHelp Never got the beta and now I’m being told I won’t get ANY of the other stuff. Including Last Jedi content and or bonus classes. Anything! :( | C6: General / Feedback / Other | E6: en | G6: active_troubleshooting | I6: true | K6: false | M6: standard | O6: Complaint regarding game pre-order beta codes and promotional content. | P6: MEDIUM | Q6: Could resemble Order & Checkout or Digital Services & Devices, but focuses on promotional extras.
A7: 25279 | B7: @AmazonHelp Yes I have contacted Amazon and this problem is going to cost me a lot of money and as of right now there is solution. | C7: General / Feedback / Other | E7: en | G7: active_troubleshooting | I7: true | K7: false | M7: standard | O7: Customer stating that previous contact did not resolve an expensive ongoing issue. | P7: MEDIUM | Q7: Could relate to multiple domains, but tweet contains no specific operational facts.
A8: 34485 | B8: @AmazonHelp Bonjour et merci. Un vendeur tiers qui ne répond pas et qui après enquête a tout l'air d'être un escroc. | C8: Seller & Product Quality | E8: fr | G8: active_troubleshooting | I8: true | K8: false | M8: standard | O8: Customer reporting non-responsive third-party marketplace seller who appears to be an escrow scammer. | P8: HIGH | Q8: Could resemble Account Access & Security due to 'escroc' (scam), but problem is 3rd-party merchant conduct.
A9: 49143 | B9: @AmazonHelp Yes but it is a robot emails! I tried and mailed several emails with my bank statement and nothing happens. Hv other email for help me? | C9: Payment, Billing & Gift Cards | E9: en | G9: active_troubleshooting | I9: true | K9: false | M9: standard | O9: Customer emailed bank statements to verify payment but received automated unhelpful responses. | P9: HIGH | Q9: Could resemble Account Access & Security if bank statement is for ID verification, but involves payment proof.
A10: 57428 | B10: @AmazonHelp It say's "Could not set your address. Please ensure you have correctly entered a complete address" when I am entering my India address | C10: General / Feedback / Other | E10: en | G10: active_troubleshooting | I10: false | K10: false | M10: standard | O10: Address input validation error when entering India shipping address. | P10: MEDIUM | Q10: Could resemble Order & Checkout, but represents address book entry error.
A11: 61025 | B11: So I change my country of residence &amp; I get charged again for prime services without mentioning that before?! #NotCool #UX 🤬 @116316 | C11: Prime & Subscription Services | E11: en | G11: new_issue | I11: true | K11: false | M11: standard | O11: Customer charged duplicate Prime membership fee upon changing country of residence without advance disclosure. | P11: HIGH | Q11: Could resemble Payment, Billing & Gift Cards due to unexpected charge, but contract issue is Prime subscription transfer.
A12: 65900 | B12: @119625 plzzz check DM | C12: General / Feedback / Other | E12: en | G12: dm_handoff | I12: false | K12: false | M12: standard | O12: Customer stating that details have been sent via Direct Message; conversational handshake. | P12: HIGH
A13: 77408 | B13: @AmazonHelp Please don't buy any product from amazon , if all thing is smooth you don't feel anytging, but if a problem happened then you see real face of so called customer centric company amazon | C13: General / Feedback / Other | E13: en | G13: active_troubleshooting | I13: false | K13: false | M13: standard | O13: Non-transactional social communication, conversational follow-up, or general inquiry. | P13: HIGH
A14: 77535 | B14: @AmazonHelp It must be. I've had the same email address for years and I have tons of old order confirmations in my inbox. | C14: General / Feedback / Other | E14: en | G14: active_troubleshooting | I14: false | K14: false | M14: standard | O14: Non-transactional social communication, conversational follow-up, or general inquiry. | P14: HIGH
A15: 83454 | B15: Pedido en @116928 este lunes (cybermonday) Esta mañana en el tracking me pone que se ha retrasado... Llega hoy. Bien @116928 Así sí | C15: General / Feedback / Other | E15: es | G15: new_issue | I15: false | K15: false | M15: standard | O15: Non-transactional social communication, conversational follow-up, or general inquiry. | P15: HIGH
A16: 86157 | B16: @115850 @AmazonHelp do you take any action when delivery boy falsely claims that he attempted delivery | C16: Delivery Problem & Logistics | E16: en | G16: new_issue | I16: true | K16: false | M16: standard | O16: Delivery carrier falsely recorded a delivery attempt without visiting customer location. | P16: HIGH
A17: 95437 | B17: @AmazonHelp - It is really poor service or has your online chat support been hacked ? | C17: Account Access & Security | E17: en | G17: new_issue | I17: true | K17: false | M17: standard | O17: Customer inquiring whether support chat has been hacked due to bizarre or degraded service experience. | P17: MEDIUM | Q17: Could resemble General / Feedback / Other due to sarcastic frustration, but explicit inquiry about hacked chat warrants security review.
A18: 105253 | B18: @AmazonHelp Ich hatte vergessen zu erwähnen, dass es ein englisches ebook ist. Wie sieht es da mit der Vorbestellergarantie aus? | C18: Digital Services & Devices | E18: de | G18: active_troubleshooting | I18: false | K18: false | M18: standard | O18: Inquiry regarding pre-order price guarantee applicability to an English digital eBook. | P18: MEDIUM | Q18: Could resemble Order & Checkout due to pre-order guarantee, but digital eBook format specifics apply.
A19: 108116 | B19: @140000 @AmazonHelp Buenos días, lamentamos lo sucedido. Os ponemos en contacto con @132703 para que os puedan ayudar a solucionarlo lo antes posible. Muchas gracias | C19: General / Feedback / Other | E19: es | G19: active_troubleshooting | I19: false | K19: false | M19: standard | O19: Non-transactional social communication, conversational follow-up, or general inquiry. | P19: HIGH
A20: 122029 | B20: O verdadeiro significado da expressão ENTREGA RÁPIDA @117086 @6926 🤓 https://t.co/Y56yLOULEv | C20: General / Feedback / Other | E20: pt | G20: new_issue | I20: false | K20: false | M20: standard | O20: Non-transactional social communication, conversational follow-up, or general inquiry. | P20: HIGH
A21: 137150 | B21: @AmazonHelp I’ve looked in there and there is no option for that, I’ve had items delivered before at the weekend | C21: General / Feedback / Other | E21: en | G21: active_troubleshooting | I21: false | K21: false | M21: standard | O21: Non-transactional social communication, conversational follow-up, or general inquiry. | P21: HIGH
A22: 139986 | B22: Sympa, quand tu commande une Yankee candle sur @120533 et qu'elle arrive en mille morceaux 😠 | C22: Delivery Problem & Logistics | E22: fr | G22: new_issue | I22: true | K22: false | M22: standard | O22: Fragile Yankee candle arrived shattered in a thousand pieces due to courier shipping handling. | P22: HIGH | Q22: Could resemble Seller & Product Quality, but shatter damage during transit is a delivery logistics failure.
A23: 140066 | B23: @AmazonHelp Voici : C20025897313 Parceque j'ai beau me plaindre à chaque fois (genre colis ouvert pour rentrer les articles 1 par 1 dans ma BaL), vous m'expediez de + en + par Amz Logistics et ça ne va pas mieux. Je vais bien finir par vous quitter hein… | C23: Delivery Problem & Logistics | E23: fr | G23: follow_up | I23: true | K23: false | M23: standard | O23: Recurring courier mishandling with packages opened and shoved into mailbox by Amazon Logistics. | P23: HIGH
A24: 142048 | B24: @AmazonHelp hey, on another note, two of my recent purchases which i asked for a return, havent been picked up yet. it's been more than two weeks. | C24: Returns, Replacements & Refunds | E24: en | G24: active_troubleshooting | I24: true | K24: false | M24: standard | O24: Return courier has failed to pick up two returned items for over two weeks. | P24: HIGH | Q24: Could resemble Delivery Problem & Logistics due to courier delay, but operation is return reverse-logistics.
A25: 142870 | B25: @AmazonHelp Tell you what I will ask is how come prime is no longer next day delivery? I’ve ordered loads of things lately over the last month and they’ve taken ages to be delivered? | C25: Delivery Problem & Logistics | E25: en | G25: active_troubleshooting | I25: true | K25: false | M25: standard | O25: Orders taking weeks despite customer paying for Prime guaranteed next-day delivery. | P25: HIGH | Q25: Mentions Prime, but under taxonomy rules late delivery complaints belong to Delivery Problem & Logistics.
A26: 162100 | B26: @AmazonHelp Ja. Komm nicht an der Info vorbei. Bei einem anderen Spiel lief es problemlos | C26: Digital Services & Devices | E26: de | G26: active_troubleshooting | I26: false | K26: false | M26: standard | O26: Customer unable to proceed past information screen in a digital gaming title where another game worked fine. | P26: HIGH | Q26: Could resemble Order & Checkout as software purchase, but is an in-game technical bug.
A27: 167890 | B27: Hoje de manhã comprei 7 livros na @117086 e já recebi email falando que foi enviado. ♡ | C27: General / Feedback / Other | E27: pt | G27: new_issue | I27: false | K27: false | M27: standard | O27: Non-transactional social communication, conversational follow-up, or general inquiry. | P27: HIGH
A28: 179265 | B28: @AmazonHelp En espérant cette fois avoir une réponse pertinente... | C28: General / Feedback / Other | E28: fr | G28: active_troubleshooting | I28: false | K28: false | M28: standard | O28: Non-transactional social communication, conversational follow-up, or general inquiry. | P28: HIGH
A29: 180800 | B29: @AmazonHelp No worries I've asked mr Jeff @115851 to do that Jeff here is the URL https://t.co/4wKCSmoFTW?amp=1 | C29: General / Feedback / Other | E29: en | G29: follow_up | I29: false | K29: false | M29: standard | O29: Non-transactional social communication, conversational follow-up, or general inquiry. | P29: HIGH
A30: 183483 | B30: @AmazonHelp ご丁寧にありがとうございます。手続きさせていただきますが、二度と同じようなことがないように対策をお願い致します。 | C30: General / Feedback / Other | E30: ja | G30: active_troubleshooting | I30: false | K30: false | M30: standard | O30: Non-transactional social communication, conversational follow-up, or general inquiry. | P30: HIGH
A31: 230015 | B31: @AmazonHelp @115850 What's the status? Will I get a refund for this fake product or not? | C31: Returns, Replacements & Refunds | E31: en | G31: active_troubleshooting | I31: true | K31: false | M31: standard | O31: Customer demanding status update on refund promised for a fake product. | P31: HIGH | Q31: Could resemble Seller & Product Quality due to fake product, but primary actionable demand is refund status.
A32: 234555 | B32: What a discount, @115850. https://t.co/9rOKTidmrp | C32: Order & Checkout | E32: en | G32: new_issue | I32: false | K32: false | M32: standard | O32: Sarcastic screenshot highlighting erroneous or broken promotional discount calculation at checkout. | P32: HIGH | Q32: Could resemble General / Feedback / Other as sarcasm, but highlights checkout promo calculation bug.
A33: 246342 | B33: @AmazonHelp I am supposed to download Alexa, right? Is it available on the android store? | C33: Digital Services & Devices | E33: en | G33: active_troubleshooting | I33: false | K33: false | M33: standard | O33: Customer inquiring how and where to download the Alexa application on an Android device. | P33: HIGH
A34: 258713 | B34: @AmazonHelp Dear Amazon, please don't try to understand "my concern"! Please post my review to help ur innocent customers. #ScamAtAmazon #Day48 | C34: Seller & Product Quality | E34: en | G34: active_troubleshooting | I34: true | K34: false | M34: standard | O34: Customer demanding publication of rejected product review to warn other buyers against poor merchandise. | P34: HIGH | Q34: Could resemble General / Feedback / Other as venting, but specifically disputes product review moderation.
A35: 268666 | B35: @AmazonHelp My software on the Roku is up-to-date and I deleted and reinstalled the Amazon Video app. It still doesn’t work. The link is for LG&amp; Samsung | C35: Digital Services & Devices | E35: en | G35: active_troubleshooting | I35: true | K35: false | M35: standard | O35: Amazon Video application crashing/freezing on Roku device after update and reinstallation. | P35: HIGH
A36: 274703 | B36: @AmazonHelp I want to knw public how u treat customer issues.. | C36: General / Feedback / Other | E36: en | G36: active_troubleshooting | I36: false | K36: false | M36: standard | O36: Non-transactional social communication, conversational follow-up, or general inquiry. | P36: HIGH
A37: 275129 | B37: @115821 Please help! Someone hacked my account and I can’t contact you on your website as they changed the email and I cannot log in! | C37: Account Access & Security | E37: en | G37: new_issue | I37: true | K37: true | M37: P0_CRITICAL | O37: Customer account hacked with email address changed preventing user login; critical security intervention required. | P37: HIGH
A38: 279337 | B38: @AmazonHelp I have already responded, but that does not resolve my problem ... I just need my money back | C38: Returns, Replacements & Refunds | E38: en | G38: active_troubleshooting | I38: true | K38: false | M38: standard | O38: Customer stating that previous replies did not resolve the problem and demanding their money back. | P38: HIGH | Q38: Could resemble General / Feedback / Other as venting, but core demand is refund reimbursement.
A39: 279504 | B39: @AmazonHelp https://t.co/gprkxWgCzm | C39: General / Feedback / Other | E39: en | G39: active_troubleshooting | I39: false | K39: false | M39: standard | O39: Non-transactional social communication, conversational follow-up, or general inquiry. | P39: HIGH
A40: 284009 | B40: @AmazonHelp @115821 No card left, no phone call to advise they were here. Reception manned 100% of the time! | C40: Delivery Problem & Logistics | E40: en | G40: active_troubleshooting | I40: true | K40: false | M40: standard | O40: Courier falsely claimed delivery attempt without calling or leaving calling card despite manned reception. | P40: HIGH
A41: 291347 | B41: @AmazonHelp If you are unable to check in your back-end &amp; have no access to it, why bother to solve? Let @115850 turn bankrupt. Customer isn't imp 4 u | C41: General / Feedback / Other | E41: en | G41: active_troubleshooting | I41: false | K41: false | M41: standard | O41: Customer expressing general corporate dissatisfaction without actionable order parameters. | P41: HIGH
A42: 320656 | B42: @AmazonHelp This was not expected from Amazon @115850 @AmazonHelp @115821 | C42: General / Feedback / Other | E42: en | G42: active_troubleshooting | I42: false | K42: false | M42: standard | O42: Non-transactional social communication, conversational follow-up, or general inquiry. | P42: HIGH
A43: 331978 | B43: @AmazonHelp If they try again today, I'll be fine. But it says next business day it will be tried. | C43: Delivery Problem & Logistics | E43: en | G43: active_troubleshooting | I43: true | K43: false | M43: standard | O43: Failed delivery attempt deferred to next business day contrary to customer availability. | P43: HIGH
A44: 341488 | B44: @AmazonHelp When ur promotion is on any social media platform, so why not ur frauds should promote &amp; should be discussed on it, Bcoz every 1 watching. | C44: General / Feedback / Other | E44: en | G44: active_troubleshooting | I44: false | K44: false | M44: standard | O44: Non-transactional social communication, conversational follow-up, or general inquiry. | P44: HIGH
A45: 379700 | B45: @AmazonHelp c'est quoi votre secret pour être aussi bien? (en vrai y'a aucun problème, c'est juste que j'attend mon colis et il devrait pas tarder :&gt; ) | C45: General / Feedback / Other | E45: fr | G45: active_troubleshooting | I45: false | K45: false | M45: standard | O45: Non-transactional social communication, conversational follow-up, or general inquiry. | P45: HIGH
A46: 379788 | B46: @115850 @115821 Recd. the wrong Item, This is not expected from you, 1st pic is what I had ordered, and second pic what I had received.. https://t.co/McMfQ2ZdRb | C46: Seller & Product Quality | E46: en | G46: new_issue | I46: true | K46: false | M46: standard | O46: Customer received completely wrong item compared to what was ordered, providing photographic proof. | P46: HIGH | Q46: Could resemble Returns, Replacements & Refunds, but customer is documenting wrong item delivered.
A47: 382736 | B47: @115850 1st ordr got delayed mltpl times den had 2 cancel it as amazon rep said it ws nly option nw no refund. Order t no- 209117266082 | C47: Returns, Replacements & Refunds | E47: en | G47: new_issue | I47: true | K47: false | M47: standard | O47: Order cancelled after multiple delivery delays, customer inquiring about missing refund. | P47: HIGH | Q47: Could resemble Delivery Problem & Logistics or Order & Checkout, but unresolved financial refund is the blocker.
A48: 388508 | B48: @AmazonHelp @115851 almost 20 days gone. I think u will provide my solution after 10 months when warranty expired.shameonyou waste services i hv seen | C48: Seller & Product Quality | E48: en | G48: active_troubleshooting | I48: true | K48: false | M48: standard | O48: Customer waiting 20 days for manufacturer/seller warranty support on a defective purchase. | P48: HIGH
A49: 391137 | B49: @AmazonHelp Si y quisiera rastrearlo y el repartidor no me lo permite! | C49: Delivery Tracking & Status | E49: es | G49: active_troubleshooting | I49: false | K49: false | M49: standard | O49: Customer wanting to track parcel in real time and asking for courier tracking access. | P49: HIGH
A50: 391184 | B50: @115850 order product worth 1033 INR, received duplicate copy of 599 INR. DISGUSTING. @AmazonHelp is it pirated copy of book? https://t.co/DLGP2swNke | C50: Seller & Product Quality | E50: en | G50: new_issue | I50: true | K50: false | M50: standard | O50: Customer received pirated/counterfeit duplicate copy of ordered book worth far less than purchase price. | P50: HIGH
A51: 397293 | B51: @115850 @AmazonHelp @1840 @115851 The worst &amp; btr exp with AmazonIn Cust Serv. Brght a mobl honor8 frm amazonIn. found it faulty. | C51: Seller & Product Quality | E51: en | G51: new_issue | I51: true | K51: false | M51: standard | O51: Customer received defective/faulty mobile phone purchased from Amazon India. | P51: HIGH
A52: 419420 | B52: @115850 how come my package was delivered saying that I recieved it? This is scary. Please explain this tracking I'd 210166006765 | C52: Delivery Problem & Logistics | E52: en | G52: new_issue | I52: true | K52: false | M52: standard | O52: Tracking falsely shows package delivered while customer has not received it. | P52: HIGH
A53: 423252 | B53: @115850 Ordered Crossbeats Raga Earphone Two months Back. The Item is defective and no longer works on the left side of the earpiece . | C53: Seller & Product Quality | E53: en | G53: new_issue | I53: true | K53: false | M53: standard | O53: Earphones developed manufacturing defect with left earpiece dead within 2 months. | P53: HIGH
A54: 451956 | B54: @AmazonHelp what is the last uk delivery date if ordering through amazon prime to ensure arrival before Xmas. If I ordered 22nd December would it arrive 23rd/24th | C54: Delivery Tracking & Status | E54: fr | G54: new_issue | I54: false | K54: false | M54: standard | O54: Inquiring about Christmas cutoff shipping dates for Prime delivery in the UK. | P54: MEDIUM | Q54: Could resemble Prime & Subscription Services, but asks about operational delivery schedule.
A55: 458992 | B55: @115821, From a long time customer, I just want to say that I've always had nothing but excellent help from @AmazonHelp. I had a couple issues with some recent orders but were quickly resolved. 👊🙌 | C55: General / Feedback / Other | E55: en | G55: resolved_or_acknowledgment | I55: false | K55: false | M55: standard | O55: Customer offering gratitude, politeness, or concluding acknowledgment of support. | P55: HIGH
A56: 459028 | B56: Amazonを名乗るアドレスから、携帯メール(SMS)で有料料金未納につき法的に訴えるという、よくある詐欺メールが来た。ご注意ください。 | C56: Account Access & Security | E56: ja | G56: new_issue | I56: true | K56: true | M56: P0_CRITICAL | O56: Phishing scam alert reporting SMS impersonating Amazon with fake legal threats for unpaid fees. | P56: HIGH | Q56: Could resemble Payment, Billing & Gift Cards due to unpaid fee claims, but external scam impersonation is an Account Access & Security concern.
A57: 460056 | B57: @AmazonHelp pq fiz o pedido no dia da promo de Black Friday. É um desconto considerável e como o "erro" foi meu, os atendentes disseram que a Amazon não mantém o desconto caso eu faça um novo pedido | C57: Order & Checkout | E57: pt | G57: active_troubleshooting | I57: true | K57: false | M57: standard | O57: Customer unable to retain Black Friday promotional discount when re-placing order. | P57: HIGH
A58: 473183 | B58: @115830 I’ve just spoken on chat and now by call to your colleagues. It is the most surreal experience I have ever had. It’s utterly appalling. Two delivery failures in 2 days... apparently Due to them not recognising our PAF compliant Postcode | C58: Delivery Problem & Logistics | E58: en | G58: new_issue | I58: true | K58: false | M58: standard | O58: Two delivery failures in two days due to courier not recognizing valid PAF postcode. | P58: HIGH
A59: 476843 | B59: @115830 Any reason why normal service has dropped over last few months, same day delivery on ANYTHING (yes you delivery to my post code) never has a cut of at 12pm and it's not available everyday as you proudly advertise either | C59: Delivery Tracking & Status | E59: en | G59: new_issue | I59: false | K59: false | M59: standard | O59: Inquiry regarding same-day delivery cutoff times and availability by postcode. | P59: MEDIUM | Q59: Could resemble Delivery Problem & Logistics, but inquires about scheduling cutoff rules.
A60: 478520 | B60: @AmazonHelp Hi! On your UK site, there’s no longer information about ‘preparing for dispatch’, etc - is it possible to see that anywhere? I’ve an order which hasn’t shipped and concerned there’s been a delay. | C60: Delivery Tracking & Status | E60: en | G60: new_issue | I60: false | K60: false | M60: standard | O60: Customer asking where to find 'preparing for dispatch' status update on UK site. | P60: HIGH
A61: 483090 | B61: @AmazonHelp Le colis n'est pas ouvert. Je suis en droit de refuser une réception de colis si le carton est endommagé non? Si je l'ouvre, il n'y a pas une invalidité de la bande de garantie? J'aimerais égalmnt accéder à cette option (la photo) afn de prouver que le livreur a signer à ma place https://t.co/eY5NbrfOUu | C61: Delivery Problem & Logistics | E61: fr | G61: active_troubleshooting | I61: true | K61: false | M61: standard | O61: Damaged outer shipping carton and courier forged customer signature on delivery receipt. | P61: HIGH
A62: 490648 | B62: @AmazonHelp Depuis la liste des commandes, impossible de contacter le vendeur. Cependant, tenter de contacter Amazon, sélectionner cette commande, et le produit qui m'intéresse… redirige vers le vendeur avec la bonne commande. Bref : 1 bogue dans votre SI + filtrage sans notification ! | C62: Seller & Product Quality | E62: fr | G62: active_troubleshooting | I62: false | K62: false | M62: standard | O62: Marketplace system bug preventing customer from contacting third-party seller from order list. | P62: MEDIUM | Q62: Could resemble Digital Services & Devices due to website bug, but core goal is contacting 3rd party seller.
A63: 498538 | B63: @AmazonHelp i just expect it to be here on the date that it initially says it going to arrive? i ordered it last minute which is a fault in my behalf but if your unique selling point is a monthly subscription for next day delivery surely that should be carried out? i won’t need this item on- | C63: Delivery Problem & Logistics | E63: fr | G63: active_troubleshooting | I63: true | K63: false | M63: standard | O63: Next-day subscription delivery failed to arrive on promised delivery date. | P63: HIGH | Q63: Customer mentions subscription USP, but issue is overdue late delivery.
A64: 500740 | B64: @AmazonHelp Have tried this stuff thousand times before but its certainly not working out as they can't find any order with my registered number. So frustrating! | C64: Seller & Product Quality | E64: en | G64: active_troubleshooting | I64: true | K64: false | M64: standard | O64: Seller or support unable to locate order record with customer registered phone number. | P64: MEDIUM | Q64: Could resemble Order & Checkout, but concerns seller/marketplace lookup failure.
A65: 508166 | B65: Errr....this was not what I ordered @115830 😺🐱🐈 https://t.co/f4VJmAw2eE | C65: Seller & Product Quality | E65: en | G65: new_issue | I65: true | K65: false | M65: standard | O65: Customer received incorrect item (cat photo/wrong product) instead of ordered goods. | P65: HIGH
A66: 519700 | B66: @AmazonHelp I just want my psn codes so me and my friends can download and play a game tonight. After I get those I'll never bother you again. | C66: Digital Services & Devices | E66: en | G66: active_troubleshooting | I66: true | K66: false | M66: standard | O66: Customer requesting delivery of purchased digital PlayStation Network (PSN) gaming codes. | P66: HIGH | Q66: Could resemble Order & Checkout, but represents digital content delivery/fulfillment.
A67: 524929 | B67: Amazon デジタルミュージック、僕の好きな80年代の曲が割と揃ってるなー。プライム会員だと結構な数聴ける。知らなかった。 | C67: Digital Services & Devices | E67: ja | G67: new_issue | I67: false | K67: false | M67: standard | O67: Customer noting audio catalog quality on Amazon Digital Music and Prime Music streaming. | P67: MEDIUM | Q67: Could resemble Prime & Subscription Services, but specifically evaluates Amazon Digital Music catalog.
A68: 532639 | B68: @AmazonHelp Schade. Da bin ich immer neugierig 😁 | C68: General / Feedback / Other | E68: de | G68: active_troubleshooting | I68: false | K68: false | M68: standard | O68: Non-transactional social communication, conversational follow-up, or general inquiry. | P68: HIGH
A69: 549521 | B69: @AmazonHelp Colis privé... seul moyen d’ouvrir c’est le pass collectif maintenant | C69: Delivery Tracking & Status | E69: fr | G69: active_troubleshooting | I69: false | K69: false | M69: standard | O69: Customer providing tracking detail regarding Colis Privé carrier access code. | P69: HIGH
A70: 575904 | B70: @AmazonHelp The link you provided doesn’t provide me the answer to my question - thanks in advance for looking into this for me if you can. If not, no worries. | C70: General / Feedback / Other | E70: en | G70: resolved_or_acknowledgment | I70: false | K70: false | M70: standard | O70: Customer offering gratitude, politeness, or concluding acknowledgment of support. | P70: HIGH
A71: 627325 | B71: @AmazonHelp Check DM | C71: General / Feedback / Other | E71: en | G71: dm_handoff | I71: false | K71: false | M71: standard | O71: Customer stating that details have been sent via Direct Message; conversational handshake. | P71: HIGH
A72: 635720 | B72: @116316 Alexa ist toll. :) | C72: Digital Services & Devices | E72: de | G72: new_issue | I72: false | K72: false | M72: standard | O72: Customer expressing satisfaction with Alexa hardware device functionality. | P72: MEDIUM | Q72: Could be classified under General / Feedback / Other as casual praise, but specifically references Alexa digital device.
A73: 649952 | B73: Amazonで別日に注文したやつが、一緒の段ボールにはいって送られて来て感動した | C73: General / Feedback / Other | E73: ja | G73: new_issue | I73: false | K73: false | M73: standard | O73: Non-transactional social communication, conversational follow-up, or general inquiry. | P73: HIGH
A74: 654327 | B74: @AmazonHelp Ok so looks like y’all didn’t put one of the items in the box | C74: Seller & Product Quality | E74: en | G74: active_troubleshooting | I74: true | K74: false | M74: standard | O74: Customer reporting that one of the ordered items was missing from the delivered package. | P74: MEDIUM | Q74: Could resemble Delivery Problem & Logistics, but missing item from sealed box represents fulfillment/packaging defect.
A75: 665249 | B75: Guys how long did the priority email take to come for @146898 tour? I’ve still not had mine 😫 #GBArmyTour #gbarmy @120474 | C75: General / Feedback / Other | E75: en | G75: new_issue | I75: false | K75: false | M75: standard | O75: Inquiry regarding tour pre-sale priority email delivery. | P75: MEDIUM | Q75: Could resemble Digital Services & Devices, but concerns third-party tour promotion.
A76: 679078 | B76: 初Amazon。 自動遮光カートリッジが安かった。 | C76: General / Feedback / Other | E76: ja | G76: new_issue | I76: false | K76: false | M76: standard | O76: Non-transactional social communication, conversational follow-up, or general inquiry. | P76: HIGH
A77: 701334 | B77: @115830 my prime now order said it wasn’t able to be delivered but I’ve been at home and had my phone on all this time. No call or attempt to contact. | C77: Delivery Problem & Logistics | E77: en | G77: new_issue | I77: true | K77: false | M77: standard | O77: Prime Now delivery recorded as failed while customer was waiting at home. | P77: HIGH
A78: 754571 | B78: @115850 Unhappy with my last order, delayed Delivery and Single sim phone instead of dual sim delivered. | C78: Delivery Problem & Logistics | E78: en | G78: new_issue | I78: true | K78: false | M78: standard | O78: Order experienced delayed delivery and wrong phone variant was received. | P78: MEDIUM | Q78: Could resemble Seller & Product Quality due to single-sim delivered, but delayed delivery is combined.
A79: 754608 | B79: I like lists and I want @115833 to make a list! | C79: General / Feedback / Other | E79: en | G79: new_issue | I79: false | K79: false | M79: standard | O79: Non-transactional social communication, conversational follow-up, or general inquiry. | P79: HIGH
A80: 780362 | B80: @AmazonHelp To be delivered before I leave! | C80: Delivery Tracking & Status | E80: en | G80: active_troubleshooting | I80: false | K80: false | M80: standard | O80: Customer following up on delivery status timing prior to departing. | P80: HIGH
A81: 786803 | B81: @AmazonHelp 後ほど調べたいと思います | C81: General / Feedback / Other | E81: ja | G81: active_troubleshooting | I81: false | K81: false | M81: standard | O81: Non-transactional social communication, conversational follow-up, or general inquiry. | P81: HIGH
A82: 810242 | B82: @AmazonHelp ...which I queried as have safe place' on my door mat' in my account. Rang cust service&amp; lovely lady apologised and emphasised delivery info | C82: Delivery Problem & Logistics | E82: fr | G82: active_troubleshooting | I82: true | K82: false | M82: standard | O82: Courier ignored safe place instructions registered on account. | P82: HIGH
A83: 845722 | B83: @115850 My ORDER # 402-0531606-9962732 dated 17th October 2017 Not delivered to me, but getting SMS, E mail update that order is delivered | C83: Delivery Problem & Logistics | E83: en | G83: new_issue | I83: true | K83: false | M83: standard | O83: Package marked as delivered via SMS/email notification but customer never received it. | P83: HIGH
A84: 852842 | B84: @117804 que saudades do meu Kindle :( | C84: Digital Services & Devices | E84: pt | G84: active_troubleshooting | I84: false | K84: false | M84: standard | O84: Customer expressing longing for their Kindle device. | P84: MEDIUM | Q84: Could resemble General / Feedback / Other as informal social expression, but directly references Kindle ecosystem.
A85: 861872 | B85: @AmazonHelp check inbox | C85: General / Feedback / Other | E85: en | G85: dm_handoff | I85: false | K85: false | M85: standard | O85: Customer stating that details have been sent via Direct Message; conversational handshake. | P85: HIGH
A86: 866150 | B86: @AmazonHelp It’s no excuse why I cants reach you thru your website about an item NO EXCUSE ! | C86: Digital Services & Devices | E86: en | G86: active_troubleshooting | I86: false | K86: false | M86: standard | O86: Customer unable to reach support through the website interface regarding an item. | P86: MEDIUM | Q86: Could resemble General / Feedback / Other, but website technical contact navigation is primary blocker.
A87: 876290 | B87: @AmazonHelp I'll do that but I'm pretty disappointed in the fact that you allow broken merchandise to go out at all. | C87: Seller & Product Quality | E87: en | G87: active_troubleshooting | I87: true | K87: false | M87: standard | O87: Disappointment expressed that broken merchandise was packaged and sent out to customer. | P87: MEDIUM | Q87: Could resemble Delivery Problem & Logistics if broken in transit, but references sending broken merchandise.
A88: 878795 | B88: @AmazonHelp i already filled form once. i called &amp; wrote email 100 times. amazon does nothing .. worst customer care in entire industry. | C88: General / Feedback / Other | E88: en | G88: follow_up | I88: false | K88: false | M88: standard | O88: Customer expressing general corporate dissatisfaction without actionable order parameters. | P88: HIGH
A89: 896490 | B89: @115850 when will u send amazon prize voucher team ??? #AmazonWoofFest17 ??? | C89: Payment, Billing & Gift Cards | E89: en | G89: active_troubleshooting | I89: false | K89: false | M89: standard | O89: Customer asking when their promotional Amazon gift card / prize voucher will be issued. | P89: HIGH | Q89: Could resemble Order & Checkout as promo, but deals with gift voucher balance issuance.
A90: 898383 | B90: @115821 nt able to buy Redmi4A used MOBILE &amp;getting Edit Quantities Error while doing checkout Called Customercare but its useless. Pls help | C90: Order & Checkout | E90: en | G90: new_issue | I90: true | K90: false | M90: standard | O90: Checkout failure with 'Edit Quantities Error' preventing purchase of phone during flash sale. | P90: HIGH
A91: 909055 | B91: @AmazonHelp Thank you so much. We order all the time and this is the first missing package. | C91: General / Feedback / Other | E91: en | G91: resolved_or_acknowledgment | I91: false | K91: false | M91: standard | O91: Customer offering gratitude, politeness, or concluding acknowledgment of support. | P91: HIGH
A92: 909507 | B92: @AmazonHelp kindly check DM Team | C92: General / Feedback / Other | E92: en | G92: dm_handoff | I92: false | K92: false | M92: standard | O92: Customer stating that details have been sent via Direct Message; conversational handshake. | P92: HIGH
A93: 944251 | B93: @AmazonHelp Done. | C93: General / Feedback / Other | E93: en | G93: active_troubleshooting | I93: false | K93: false | M93: standard | O93: Non-transactional social communication, conversational follow-up, or general inquiry. | P93: HIGH
A94: 947686 | B94: @115850 @AmazonHelp why you send me the ordered product after expected date of delivery most of the time.Also send me expired product | C94: Seller & Product Quality | E94: en | G94: new_issue | I94: true | K94: false | M94: standard | O94: Customer received expired product from seller. | P94: MEDIUM | Q94: Also mentions late delivery, but receipt of expired perishable merchandise is a product quality breach.
A95: 953129 | B95: @AmazonHelp @115821 Honesty, I blame myself for relying too much on @115821. I should have known. | C95: General / Feedback / Other | E95: en | G95: active_troubleshooting | I95: false | K95: false | M95: standard | O95: Non-transactional social communication, conversational follow-up, or general inquiry. | P95: HIGH
A96: 962503 | B96: なんかアマゾンで返品したら、送料も半額くらい帰ってきたけど、どこで返金判断出来るんやろクレカで | C96: Returns, Replacements & Refunds | E96: ja | G96: new_issue | I96: false | K96: false | M96: standard | O96: Inquiry regarding how and where a partial return shipping refund will appear on credit card. | P96: HIGH | Q96: Could resemble Payment, Billing & Gift Cards, but refund originates directly from an item return.
A97: 984200 | B97: @AmazonHelp This is not an issue with the book (although Amazon could look into splitting this into 2 pages?) but with Kindle for PC. | C97: Digital Services & Devices | E97: en | G97: active_troubleshooting | I97: false | K97: false | M97: standard | O97: Display/formatting bug report with Kindle for PC application rendering split pages. | P97: HIGH
A98: 1021059 | B98: @AmazonHelp I sent a request, thank you. | C98: General / Feedback / Other | E98: en | G98: resolved_or_acknowledgment | I98: false | K98: false | M98: standard | O98: Customer offering gratitude, politeness, or concluding acknowledgment of support. | P98: HIGH
A99: 1034669 | B99: @AmazonHelp Kindly check DM | C99: General / Feedback / Other | E99: en | G99: dm_handoff | I99: false | K99: false | M99: standard | O99: Customer stating that details have been sent via Direct Message; conversational handshake. | P99: HIGH
A100: 1046123 | B100: @127187...congratulations for making amazon india's fake and fraudlent company. am sending legal notice to you nd jeff shortly. | C100: Seller & Product Quality | E100: en | G100: new_issue | I100: true | K100: false | M100: standard | O100: Customer alleging fraudulent/counterfeit goods and threatening legal notice to corporate management. | P100: HIGH | Q100: Could resemble General / Feedback / Other as legal threat venting, but alleges fake products.
A101: 1053594 | B101: @AmazonHelp I have a complaint against your seller then! | C101: Seller & Product Quality | E101: en | G101: active_troubleshooting | I101: true | K101: false | M101: standard | O101: Customer lodging an explicit grievance against third-party marketplace seller. | P101: HIGH
...

Sheet Taxonomy
A1: Intent Name | B1: Operational Scope & Definition | C1: Inclusion Criteria | D1: Exclusion Criteria | E1: Real Dataset Example | F1: Closest Competing Intent & Boundary Rule
A2: Delivery Tracking & Status | B2: Inquiries regarding package transit status, carrier information, or ETA while order is STILL WITHIN expected delivery SLA window. | C2: Asking tracking number, carrier name, ETA, dispatch timeline before SLA breach. | D2: Package overdue, delayed, marked delivered but missing, courier misconduct -> Delivery Problem & Logistics. | E2: @AmazonHelp the second item to be delivered today, maybe. Not updated tracking since Tuesday. Tracking useless | F2: Competing: Delivery Problem & Logistics. Rule: If package is overdue, missed date, or marked delivered but not received, it is Delivery Problem & Logistics.
A3: Delivery Problem & Logistics | B3: Escalations concerning a failure in the physical delivery, fulfillment, or doorstep handover of an order. | C3: Orders overdue, missed promised date/time, false delivery claims ('customer not home'), delivered but missing, crushed shipping boxes. | D3: Package in transit within SLA -> Delivery Tracking. Inquiring how to return damaged goods -> Returns. Defective product manufacturing -> Seller & Product Quality. | E3: @AmazonHelp Thanks. Expected 8 October. 9 October almost done and still not delivered. Contacting you for assistance not easy. | F3: Competing: Delivery Tracking & Status / Prime. Rule: If customer mentions Prime only regarding a late package ('I pay for Prime, why is it late?'), it is Delivery Problem & Logistics.
A4: Returns, Replacements & Refunds | B4: Requests or inquiries concerning returning an item, exchanging/replacing an item, obtaining return labels, or tracking return/cancellation refunds. | C4: Return process questions, replacement/exchange requests, return drop-off logistics, refund status for returned or cancelled orders. | D4: Unrecognized card charges -> Payment, Billing. General defect without return request -> Seller & Product Quality. Pre-dispatch cancellation -> Order & Checkout. | E4: @AmazonHelp very bad customer support i order a product and receive defective product and again apply for order refund but no response. | F4: Competing: Payment, Billing & Gift Cards. Rule: If money is owed as a result of a return, exchange, or order cancellation, classify under Returns, Replacements & Refunds.
A5: Payment, Billing & Gift Cards | B5: Inquiries and disputes regarding payment processing, unauthorized charges, double debits, gift cards, Amazon Pay balance, COD rules, and tax invoices. | C5: Double charges, unrecognized debit on bank statement, payment declined, gift card claim failure, Cash on Delivery disputes, official GST invoices. | D5: Refund owed from returned item -> Returns, Replacements & Refunds. Prime subscription auto-renew fee -> Prime. Account takeover fraud -> Account Access. | E5: @AmazonHelp I think I’ve been charged for my items individually rather than in one go. | F5: Competing: Returns, Replacements & Refunds. Rule: Charges originating from Amazon checkout, gift card balances, invoices, or COD belong here. Refunds from physical returns belong in Returns.
A6: Prime & Subscription Services | B6: Inquiries strictly concerning Amazon Prime membership contract, subscription fees, auto-renewal, student Prime, or subscription benefits (Prime Music, Kindle Unlimited). | C6: Prime sign-up, free trial terms, auto-renewal settings, cancellation requests, membership fees, Prime Student verification. | D6: Complaining that Prime package arrived late -> Delivery Problem & Logistics. Prime Video app crashing -> Digital Services. Returning Prime purchase -> Returns. | E6: Amazonプライム勝手に継続登録になって無駄にお金払ってから約半年... 来年もプライム会員継続しようかと心揺れてる (Auto-renewed Prime without realizing) | F6: Competing: Delivery Problem & Logistics. Rule: Use Prime & Subscription Services ONLY when the subject of inquiry is the membership contract itself. Late Prime deliveries belong in Delivery Problem.
A7: Order & Checkout | B7: Pre-fulfillment order management and purchasing issues: canceling prior to shipment, changing address before dispatch, promo codes failing, checkout errors. | C7: Canceling order before shipping, modifying delivery speed/address before fulfillment, promo codes/coupons failing at cart, lightning deal pricing glitches. | D7: Order already shipped and customer wants to track it -> Delivery Tracking. Order delivered and customer wants to return -> Returns. Card declined -> Payment. | E7: @AmazonHelp And secondly I would like to know if it was out of stock how I was able to place the order | F7: Competing: Returns, Replacements & Refunds. Rule: Pre-dispatch modifications or cart/deal issues belong to Order & Checkout. Post-dispatch cancellation belongs to Returns.
A8: Account Access & Security | B8: Inquiries regarding Amazon authentication, login credentials, two-factor authentication (2FA/OTP), locked accounts, and critical security issues (hacked account, phishing SMS). | C8: Unable to sign in, forgotten password, 2FA/OTP verification code not received, account suspended/locked, phishing emails/SMS, compromised credentials. | D8: Regular billing inquiry on active account -> Payment. Accessing specific Kindle eBook -> Digital Services. | E8: @115821 Please help! Someone hacked my account and I can’t contact you on your website as they changed the email and I cannot log in! | F8: Competing: Payment, Billing & Gift Cards. Rule: If the barrier prevents authentication or involves security/fraud/scams, classify under Account Access & Security with is_security_alert: true when malicious.
A9: Digital Services & Devices | B9: Technical support, device setup, and content delivery for Amazon hardware (Kindle, Echo/Alexa, Fire TV) and digital services (Prime Video streaming, Amazon Music, app crashes). | C9: Hardware setup/malfunction, Prime Video playback buffering/errors, Kindle eBook download failures, Amazon mobile app/website technical errors. | D9: Inquiries about Prime subscription pricing -> Prime & Subscription Services. Non-Amazon physical products defective -> Seller & Product Quality. | E9: @116618 glad I can watch Thursday night football with prime. But please address the quality and consistency with your streaming service when it comes to live football. | F9: Competing: Prime & Subscription Services. Rule: Technical glitches, streaming errors, app crashes, and Alexa/Kindle hardware issues belong here. Subscription contracts belong in Prime.
A10: Seller & Product Quality | B10: Grievances regarding physical product condition, manufacturing defects, counterfeit/fake items, 3rd-party marketplace seller unresponsiveness, or review rejections. | C10: Accusations of fake/counterfeit goods, defective items, broken merchandise, misleading product listings, 3rd-party seller disputes, product review moderation disputes. | D10: Product damaged solely because courier crushed outer shipping box -> Delivery Problem & Logistics. Customer explicitly requesting return label/refund -> Returns. | E10: @115850 I ordered dymatize whey protein and its fake.. it doesn’t taste like vanilla it has poor packaging.. customer care no. On hologram doesn’t work. | F10: Competing: Returns, Replacements & Refunds. Rule: If the customer is describing the defect, fake item, or seller grievance, classify under Seller & Product Quality. If demanding the return/refund process, classify under Returns.
A11: General / Feedback / Other | B11: Non-transactional communications, general feedback, customer appreciation, unspecific venting, conversational handshakes ('check DM'), and social media chatter. | C11: Customer praise/thanks, general venting without specific order details, conversational DM handshakes ('Sent DM', 'check inbox'), polite closings. | D11: Any message that articulates an actionable order, delivery, payment, account, or product issue -> Route to the specific business intent. | E11: @AmazonHelp Done, your customer service rep was most helpful! | F11: Competing: None (catch-all for non-actionable turns). Rule: Use General / Feedback / Other ONLY when there is no actionable transaction or specific problem matching classes 1-9.

Sheet Decision Rules
A1: Principle / Policy Area | B1: Core Operational Rule | C1: Implementation Standard & Examples
A2: 1. Separation of Concerns: Language | B2: LANGUAGE IS METADATA, NOT INTENT. | C2: Customer language is captured in 'language' ('en', 'es', 'ja', 'de', 'pt', 'fr', 'it', 'other'). Multilingual queries must be classified into their true underlying business intent.
A3: 2. Separation of Concerns: Conversation State | B3: CONVERSATION STATE IS DIALOGUE PHASE, NOT INTENT. | C3: Captured in 'conversation_state': 'new_issue' (opener), 'active_troubleshooting' (mid-thread diagnosis), 'dm_handoff' ('check DM'), 'follow_up' (providing requested details), 'resolved_or_acknowledgment' ('thanks/done'), 'unclear' (fragmentary).
A4: 3. Separation of Concerns: Escalation & Priority | B4: ESCALATION AND SECURITY ARE NOT SEPARATE ROUTING INTENTS. | C4: Fraud, phishing, and account takeover are classified under 'Account Access & Security' with orthogonal attributes 'is_security_alert: true' and 'priority: P0_CRITICAL'.
A5: 4. Escalation Decision Protocol | B5: SET ESCALATE=TRUE WHEN HUMAN AGENT INTERVENTION IS REQUIRED. | C5: Set true when: security/phishing threat exists, account compromise suspected, high-risk financial dispute, needs account/order-specific intervention that automated systems cannot execute, or customer is escalating. Set false when routine FAQ/guidance or standard tracking suffices.
A6: 5. Critical Boundary: Tracking vs Problem | B6: IN-TRANSIT SLA INTEGRITY GOVERNS ROUTING. | C6: If package is still within promised SLA delivery window without reported failure -> 'Delivery Tracking & Status'. If package is late, missed date/time, false attempt scan, or marked delivered but missing -> 'Delivery Problem & Logistics'.
A7: 6. Critical Boundary: Prime vs Delivery Problem | B7: THE CORE OBJECT OF INQUIRY GOVERNS ROUTING. | C7: If customer mentions Prime only to emphasize late delivery ('I pay for Prime, why is my delivery late?') -> 'Delivery Problem & Logistics'. Classify under 'Prime & Subscription Services' ONLY if the inquiry concerns subscription terms, fees, or cancellation.
A8: 7. Critical Boundary: Return vs Payment/Billing | B8: TRANSACTION ORIGIN GOVERNS REFUNDS. | C8: If money is owed resulting from a returned item, exchange, or cancelled order -> 'Returns, Replacements & Refunds'. If the dispute is about unexpected checkout debits, invoices, gift card balances, or COD -> 'Payment, Billing & Gift Cards'.
A9: 8. Critical Boundary: Product Quality vs Returns | B9: CUSTOMER'S PRIMARY ACTIONABLE DEMAND GOVERNS ROUTING. | C9: If message primarily details a defect, fake item, or seller grievance -> 'Seller & Product Quality'. If customer has moved past describing the defect and is explicitly requesting the return label or refund -> 'Returns, Replacements & Refunds'.

Sheet Difficult Cases
A1: message_id | B1: original_text | C1: proposed_intent | D1: alternative_intent | E1: ambiguity_rationale
A2: 1721 | B2: @AmazonHelp Never got the beta and now I’m being told I won’t get ANY of the other stuff. Including Last Jedi content and or bonus classes. Anything! :( | C2: General / Feedback / Other | D2: Order & Checkout or Digital Services & Devices, | E2: Could resemble Order & Checkout or Digital Services & Devices, but focuses on promotional extras.
A3: 25279 | B3: @AmazonHelp Yes I have contacted Amazon and this problem is going to cost me a lot of money and as of right now there is solution. | C3: General / Feedback / Other | D3: Alternative Category | E3: Could relate to multiple domains, but tweet contains no specific operational facts.
A4: 34485 | B4: @AmazonHelp Bonjour et merci. Un vendeur tiers qui ne répond pas et qui après enquête a tout l'air d'être un escroc. | C4: Seller & Product Quality | D4: Account Access & Security | E4: Could resemble Account Access & Security due to 'escroc' (scam), but problem is 3rd-party merchant conduct.
A5: 49143 | B5: @AmazonHelp Yes but it is a robot emails! I tried and mailed several emails with my bank statement and nothing happens. Hv other email for help me? | C5: Payment, Billing & Gift Cards | D5: Account Access & Security if bank statement is for ID verification, | E5: Could resemble Account Access & Security if bank statement is for ID verification, but involves payment proof.
A6: 57428 | B6: @AmazonHelp It say's "Could not set your address. Please ensure you have correctly entered a complete address" when I am entering my India address | C6: General / Feedback / Other | D6: Order & Checkout, | E6: Could resemble Order & Checkout, but represents address book entry error.
A7: 61025 | B7: So I change my country of residence &amp; I get charged again for prime services without mentioning that before?! #NotCool #UX 🤬 @116316 | C7: Prime & Subscription Services | D7: Payment, Billing & Gift Cards | E7: Could resemble Payment, Billing & Gift Cards due to unexpected charge, but contract issue is Prime subscription transfer.
A8: 95437 | B8: @AmazonHelp - It is really poor service or has your online chat support been hacked ? | C8: Account Access & Security | D8: General / Feedback / Other | E8: Could resemble General / Feedback / Other due to sarcastic frustration, but explicit inquiry about hacked chat warrants security review.
A9: 105253 | B9: @AmazonHelp Ich hatte vergessen zu erwähnen, dass es ein englisches ebook ist. Wie sieht es da mit der Vorbestellergarantie aus? | C9: Digital Services & Devices | D9: Order & Checkout | E9: Could resemble Order & Checkout due to pre-order guarantee, but digital eBook format specifics apply.
A10: 139986 | B10: Sympa, quand tu commande une Yankee candle sur @120533 et qu'elle arrive en mille morceaux 😠 | C10: Delivery Problem & Logistics | D10: Seller & Product Quality, | E10: Could resemble Seller & Product Quality, but shatter damage during transit is a delivery logistics failure.
A11: 142048 | B11: @AmazonHelp hey, on another note, two of my recent purchases which i asked for a return, havent been picked up yet. it's been more than two weeks. | C11: Returns, Replacements & Refunds | D11: Delivery Problem & Logistics | E11: Could resemble Delivery Problem & Logistics due to courier delay, but operation is return reverse-logistics.
A12: 142870 | B12: @AmazonHelp Tell you what I will ask is how come prime is no longer next day delivery? I’ve ordered loads of things lately over the last month and they’ve taken ages to be delivered? | C12: Delivery Problem & Logistics | D12: Alternative Category | E12: Mentions Prime, but under taxonomy rules late delivery complaints belong to Delivery Problem & Logistics.
A13: 162100 | B13: @AmazonHelp Ja. Komm nicht an der Info vorbei. Bei einem anderen Spiel lief es problemlos | C13: Digital Services & Devices | D13: Order & Checkout as software purchase, | E13: Could resemble Order & Checkout as software purchase, but is an in-game technical bug.
... A31: 754571 | B31: @115850 Unhappy with my last order, delayed Delivery and Single sim phone instead of dual sim delivered. | C31: Delivery Problem & Logistics | D31: Seller & Product Quality | E31: Could resemble Seller & Product Quality due to single-sim delivered, but delayed delivery is combined.

Sheet Agreement Analysis
A1: ASSISTANT VS HUMAN ANNOTATION AGREEMENT ANALYSIS
A2: NOTE: These are annotation-assistance agreement statistics measuring alignment between assistant proposals and human gold labels. They do NOT represent AI customer-support agent model evaluation accuracy.
A4: Evaluation Dimension | B4: Assistant Proposed Field | C4: Human Gold Field | D4: Completed Reviews | E4: Matching Agreements | F4: Agreement Rate
A5: Intent Classification | B5: C6:C205 | C5: D6:D205 | D5: =COUNTA(Review!D6:D205) | E5: =IF(COUNTA(Review!D6:D205)=0, 0, SUMPRODUCT(--(Review!C6:C205=Review!D6:D205))) | F5: =IF(COUNTA(Review!D6:D205)=0, "Pending Review", SUMPRODUCT(--(Review!C6:C205=Review!D6:D205))/COUNTA(Review!D6:D205))
A6: Language Detection | B6: E6:E205 | C6: F6:F205 | D6: =COUNTA(Review!F6:F205) | E6: =IF(COUNTA(Review!F6:F205)=0, 0, SUMPRODUCT(--(Review!E6:E205=Review!F6:F205))) | F6: =IF(COUNTA(Review!F6:F205)=0, "Pending Review", SUMPRODUCT(--(Review!E6:E205=Review!F6:F205))/COUNTA(Review!F6:F205))
A7: Conversation State | B7: G6:G205 | C7: H6:H205 | D7: =COUNTA(Review!H6:H205) | E7: =IF(COUNTA(Review!H6:H205)=0, 0, SUMPRODUCT(--(Review!G6:G205=Review!H6:H205))) | F7: =IF(COUNTA(Review!H6:H205)=0, "Pending Review", SUMPRODUCT(--(Review!G6:G205=Review!H6:H205))/COUNTA(Review!H6:H205))
A8: Escalation Routing | B8: I6:I205 | C8: J6:J205 | D8: =COUNTA(Review!J6:J205) | E8: =IF(COUNTA(Review!J6:J205)=0, 0, SUMPRODUCT(--(Review!I6:I205=Review!J6:J205))) | F8: =IF(COUNTA(Review!J6:J205)=0, "Pending Review", SUMPRODUCT(--(Review!I6:I205=Review!J6:J205))/COUNTA(Review!J6:J205))
A9: Security Alert Flag | B9: K6:K205 | C9: L6:L205 | D9: =COUNTA(Review!L6:L205) | E9: =IF(COUNTA(Review!L6:L205)=0, 0, SUMPRODUCT(--(Review!K6:K205=Review!L6:L205))) | F9: =IF(COUNTA(Review!L6:L205)=0, "Pending Review", SUMPRODUCT(--(Review!K6:K205=Review!L6:L205))/COUNTA(Review!L6:L205))
A10: Escalation Priority | B10: M6:M205 | C10: N6:N205 | D10: =COUNTA(Review!N6:N205) | E10: =IF(COUNTA(Review!N6:N205)=0, 0, SUMPRODUCT(--(Review!M6:M205=Review!N6:N205))) | F10: =IF(COUNTA(Review!N6:N205)=0, "Pending Review", SUMPRODUCT(--(Review!M6:M205=Review!N6:N205))/COUNTA(Review!N6:N205))
